{"entries":[{"playerName":"DRipPyyNUTss","playerDisplayName":"DRipPyyNUTss§r","prefix":"","suffix":"","playerID":"bcd68ba0-7691-3df8-b1fd-4cee0da1b1e7","position":1,"board":"statistic_hours_played","type":"MONTHLY","score":10.0},{"playerName":"Uv_Yt_OP","playerDisplayName":"Uv_Yt_OP§r","prefix":"","suffix":"","playerID":"f15ed650-335b-3175-a6f9-5a0e3a928475","position":2,"board":"statistic_hours_played","type":"MONTHLY","score":8.0},{"playerName":"HowToCrits_","playerDisplayName":"HowToCrits_§r","prefix":"","suffix":"","playerID":"eba76500-3ede-32ff-9dc5-b859dcc80919","position":3,"board":"statistic_hours_played","type":"MONTHLY","score":8.0},{"playerName":"Supremeworks","playerDisplayName":"Supremeworks§r","prefix":"","suffix":"","playerID":"814cd020-91e9-396c-a27b-c24e23bd3fca","position":4,"board":"statistic_hours_played","type":"MONTHLY","score":6.0},{"playerName":"RxnZyy","playerDisplayName":"RxnZyy§r","prefix":"","suffix":"","playerID":"54a5ea30-6d36-30da-a4e6-e70318e9cb8d","position":5,"board":"statistic_hours_played","type":"MONTHLY","score":6.0},{"playerName":"NimonX","playerDisplayName":"NimonX§r","prefix":"","suffix":"","playerID":"f463339e-10ea-3fd4-b22f-ebec0493d145","position":6,"board":"statistic_hours_played","type":"MONTHLY","score":6.0},{"playerName":"oWhatsKB","playerDisplayName":"oWhatsKB§r","prefix":"","suffix":"","playerID":"c27fdaf7-5791-337c-aa25-59185f83dafd","position":7,"board":"statistic_hours_played","type":"MONTHLY","score":5.0},{"playerName":"Ishita_xd","playerDisplayName":"Ishita_xd§r","prefix":"","suffix":"","playerID":"177c19a1-1da5-331c-9ae3-6d4a2ff22a6c","position":8,"board":"statistic_hours_played","type":"MONTHLY","score":5.0},{"playerName":"Immxrtal_Aryxn","playerDisplayName":"Immxrtal_Aryxn§r","prefix":"","suffix":"","playerID":"682db91c-e983-3b83-b6a9-ffc1d9660477","position":9,"board":"statistic_hours_played","type":"MONTHLY","score":5.0},{"playerName":"Etz_xe0n","playerDisplayName":"Etz_xe0n§r","prefix":"","suffix":"","playerID":"25e3258c-faff-3c06-ac86-af6ae3498e68","position":10,"board":"statistic_hours_played","type":"MONTHLY","score":5.0}],"meta":{"time":1701426867370,"type":"MONTHLY","board":"statistic_hours_played"}}