{"stats":{"minecraft:dropped":{"minecraft:cobblestone":4,"minecraft:golden_apple":1},"minecraft:used":{"minecraft:rail":2,"minecraft:diamond_pickaxe":35,"minecraft:water_bucket":12,"minecraft:netherite_sword":3,"minecraft:golden_apple":14,"minecraft:diamond_sword":2,"minecraft:lava_bucket":7,"minecraft:firework_rocket":4,"minecraft:cobblestone":105,"minecraft:bow":33,"minecraft:bucket":17,"minecraft:tnt_minecart":2,"minecraft:ender_pearl":19,"minecraft:shield":19,"minecraft:cooked_beef":2,"minecraft:diamond_axe":10,"minecraft:splash_potion":12,"minecraft:totem_of_undying":5,"minecraft:cobweb":40},"minecraft:killed_by":{"minecraft:player":13},"minecraft:picked_up":{"minecraft:string":1,"minecraft:cobblestone":35},"minecraft:custom":{"minecraft:time_since_rest":7206,"minecraft:damage_absorbed":811,"minecraft:crouch_one_cm":949,"minecraft:play_time":45474,"minecraft:sprint_one_cm":208316,"minecraft:damage_taken":5701,"minecraft:walk_one_cm":60094,"minecraft:deaths":13,"minecraft:damage_blocked_by_shield":2112,"minecraft:sneak_time":941,"minecraft:walk_under_water_one_cm":1592,"minecraft:drop":5,"minecraft:jump":662,"minecraft:damage_dealt":315,"minecraft:leave_game":1,"minecraft:walk_on_water_one_cm":2481,"minecraft:time_since_death":7206,"minecraft:total_world_time":45474,"minecraft:damage_dealt_absorbed":242,"minecraft:fall_one_cm":13838,"minecraft:fly_one_cm":131217},"minecraft:mined":{"minecraft:cobblestone":35}},"DataVersion":3337}