{"stats":{"minecraft:used":{"minecraft:netherite_sword":418,"minecraft:water_bucket":48,"minecraft:diamond_pickaxe":3,"minecraft:lava_bucket":77,"minecraft:oak_planks":123,"minecraft:tnt_minecart":3,"minecraft:ender_pearl":29,"minecraft:shield":3,"minecraft:totem_of_undying":13,"minecraft:diamond_axe":44,"minecraft:golden_apple":130,"minecraft:respawn_anchor":8,"minecraft:diamond_sword":274,"minecraft:glowstone":22,"minecraft:rail":3,"minecraft:cobblestone":277,"minecraft:bow":163,"minecraft:end_crystal":56,"minecraft:bucket":110,"minecraft:crossbow":4,"minecraft:cooked_beef":1,"minecraft:splash_potion":31,"minecraft:experience_bottle":128,"minecraft:cobweb":53,"minecraft:obsidian":28},"minecraft:killed_by":{"minecraft:player":14},"minecraft:picked_up":{"minecraft:green_terracotta":1,"minecraft:string":19,"minecraft:dirt":19,"minecraft:tnt_minecart":1,"minecraft:glowstone_dust":3,"minecraft:cobblestone":2},"minecraft:custom":{"minecraft:time_since_rest":765,"minecraft:damage_absorbed":4827,"minecraft:sprint_one_cm":249319,"minecraft:damage_taken":20102,"minecraft:walk_one_cm":511241,"minecraft:damage_blocked_by_shield":299,"minecraft:damage_dealt":10026,"minecraft:player_kills":6,"minecraft:fly_one_cm":226129,"minecraft:damage_dealt_absorbed":4034,"minecraft:swim_one_cm":320,"minecraft:crouch_one_cm":4399,"minecraft:play_time":118084,"minecraft:deaths":14,"minecraft:sneak_time":4092,"minecraft:walk_under_water_one_cm":6910,"minecraft:jump":3324,"minecraft:leave_game":6,"minecraft:time_since_death":765,"minecraft:walk_on_water_one_cm":35875,"minecraft:total_world_time":118084,"minecraft:fall_one_cm":76186},"minecraft:mined":{"minecraft:glowstone":2,"minecraft:cobweb":2,"minecraft:cobblestone":2}},"DataVersion":3337}