{"stats":{"minecraft:used":{"minecraft:respawn_anchor":11,"minecraft:golden_apple":11,"minecraft:netherite_sword":18,"minecraft:glowstone":8,"minecraft:end_crystal":47,"minecraft:ender_pearl":9,"minecraft:splash_potion":3,"minecraft:totem_of_undying":16,"minecraft:obsidian":12},"minecraft:killed_by":{"minecraft:player":5},"minecraft:picked_up":{"minecraft:glowstone_dust":3},"minecraft:custom":{"minecraft:time_since_rest":313,"minecraft:damage_absorbed":1293,"minecraft:deaths":5,"minecraft:play_time":17499,"minecraft:sprint_one_cm":48973,"minecraft:walk_one_cm":49318,"minecraft:damage_taken":4377,"minecraft:sneak_time":39,"minecraft:jump":100,"minecraft:damage_dealt":120,"minecraft:leave_game":5,"minecraft:time_since_death":313,"minecraft:total_world_time":17499,"minecraft:damage_dealt_absorbed":575,"minecraft:fall_one_cm":34347,"minecraft:fly_one_cm":24291}},"DataVersion":3337}