{"stats":{"minecraft:mined":{"minecraft:obsidian":6,"minecraft:rail":1,"minecraft:cobweb":2},"minecraft:used":{"minecraft:water_bucket":5,"minecraft:netherite_sword":659,"minecraft:netherite_axe":7,"minecraft:oak_planks":102,"minecraft:tnt_minecart":21,"minecraft:ender_pearl":75,"minecraft:shield":12,"minecraft:diamond_axe":32,"minecraft:blue_bed":1,"minecraft:totem_of_undying":24,"minecraft:golden_sword":2,"minecraft:golden_apple":201,"minecraft:respawn_anchor":4,"minecraft:fishing_rod":39,"minecraft:diamond_sword":69,"minecraft:rail":16,"minecraft:bow":126,"minecraft:end_crystal":82,"minecraft:bucket":5,"minecraft:netherite_pickaxe":6,"minecraft:crossbow":66,"minecraft:splash_potion":106,"minecraft:cobweb":103,"minecraft:obsidian":33},"minecraft:picked_up":{"minecraft:string":3,"minecraft:obsidian":6,"minecraft:rail":8},"minecraft:killed_by":{"minecraft:player":20},"minecraft:custom":{"minecraft:time_since_rest":11465,"minecraft:walk_one_cm":478586,"minecraft:damage_absorbed":5950,"minecraft:sprint_one_cm":183535,"minecraft:damage_taken":31796,"minecraft:damage_blocked_by_shield":1861,"minecraft:damage_dealt":8710,"minecraft:player_kills":5,"minecraft:damage_dealt_absorbed":3292,"minecraft:fly_one_cm":317278,"minecraft:crouch_one_cm":20004,"minecraft:deaths":21,"minecraft:play_time":123988,"minecraft:sneak_time":7642,"minecraft:walk_under_water_one_cm":13,"minecraft:jump":2535,"minecraft:leave_game":6,"minecraft:time_since_death":11465,"minecraft:walk_on_water_one_cm":4911,"minecraft:climb_one_cm":1076,"minecraft:total_world_time":123988,"minecraft:fall_one_cm":57966}},"DataVersion":3337}