{"stats":{"minecraft:used":{"minecraft:golden_apple":2,"minecraft:netherite_sword":3,"minecraft:rail":5,"minecraft:bow":7,"minecraft:tnt_minecart":2,"minecraft:end_stone":5,"minecraft:blue_bed":4},"minecraft:killed_by":{"minecraft:player":1},"minecraft:picked_up":{"minecraft:end_stone":22},"minecraft:custom":{"minecraft:time_since_rest":95,"minecraft:walk_one_cm":5240,"minecraft:damage_taken":720,"minecraft:play_time":3521,"minecraft:crouch_one_cm":55,"minecraft:sprint_one_cm":12458,"minecraft:deaths":2,"minecraft:damage_absorbed":82,"minecraft:sneak_time":19,"minecraft:jump":26,"minecraft:damage_dealt":0,"minecraft:leave_game":1,"minecraft:time_since_death":94,"minecraft:total_world_time":3521,"minecraft:damage_dealt_absorbed":90,"minecraft:fall_one_cm":11391,"minecraft:fly_one_cm":6837}},"DataVersion":3337}