{"stats":{"minecraft:used":{"minecraft:wooden_axe":2,"minecraft:water_bucket":6,"minecraft:netherite_sword":297,"minecraft:lava_bucket":9,"minecraft:flint_and_steel":9,"minecraft:slime_block":2,"minecraft:netherite_axe":2,"minecraft:ender_pearl":20,"minecraft:shield":30,"minecraft:iron_sword":47,"minecraft:diamond_axe":152,"minecraft:totem_of_undying":2,"minecraft:golden_apple":42,"minecraft:respawn_anchor":39,"minecraft:fishing_rod":60,"minecraft:diamond_sword":462,"minecraft:wooden_sword":4,"minecraft:cobblestone":275,"minecraft:bow":60,"minecraft:end_crystal":1,"minecraft:tnt":9,"minecraft:bucket":12,"minecraft:crossbow":86,"minecraft:cooked_beef":17,"minecraft:splash_potion":67,"minecraft:cobweb":27,"minecraft:obsidian":8},"minecraft:killed_by":{"minecraft:player":42},"minecraft:picked_up":{"minecraft:black_terracotta":13,"minecraft:sand":16,"minecraft:string":1,"minecraft:red_sand":16},"minecraft:custom":{"minecraft:time_since_rest":1937,"minecraft:walk_one_cm":178426,"minecraft:damage_absorbed":1641,"minecraft:sprint_one_cm":366261,"minecraft:damage_taken":21463,"minecraft:damage_blocked_by_shield":2202,"minecraft:damage_dealt":13687,"minecraft:damage_dealt_absorbed":1764,"minecraft:fly_one_cm":1251532,"minecraft:player_kills":17,"minecraft:crouch_one_cm":5323,"minecraft:play_time":123590,"minecraft:deaths":42,"minecraft:sneak_time":2991,"minecraft:jump":5478,"minecraft:leave_game":5,"minecraft:time_since_death":1937,"minecraft:walk_on_water_one_cm":3372,"minecraft:total_world_time":123590,"minecraft:fall_one_cm":92452}},"DataVersion":3337}