{"stats":{"minecraft:custom":{"minecraft:time_since_rest":7920,"minecraft:damage_absorbed":1750,"minecraft:crouch_one_cm":533,"minecraft:play_time":13028,"minecraft:sprint_one_cm":31614,"minecraft:deaths":1,"minecraft:damage_taken":5128,"minecraft:walk_one_cm":33182,"minecraft:sneak_time":1002,"minecraft:jump":190,"minecraft:damage_dealt":4,"minecraft:leave_game":2,"minecraft:time_since_death":7920,"minecraft:total_world_time":13028,"minecraft:fly_one_cm":46943,"minecraft:damage_dealt_absorbed":1308,"minecraft:fall_one_cm":9016,"minecraft:player_kills":3},"minecraft:picked_up":{"minecraft:glowstone_dust":1,"minecraft:dirt":130},"minecraft:used":{"minecraft:respawn_anchor":41,"minecraft:golden_apple":38,"minecraft:glowstone":22,"minecraft:dirt":2,"minecraft:end_crystal":60,"minecraft:netherite_pickaxe":12,"minecraft:ender_pearl":29,"minecraft:totem_of_undying":22,"minecraft:obsidian":31},"minecraft:killed_by":{"minecraft:player":1},"minecraft:mined":{"minecraft:grass_block":1,"minecraft:dirt":4,"minecraft:obsidian":11}},"DataVersion":3337}