{"stats":{"minecraft:used":{"minecraft:ender_pearl":1,"minecraft:diamond_sword":1},"minecraft:custom":{"minecraft:jump":151,"minecraft:time_since_rest":4272,"minecraft:leave_game":1,"minecraft:crouch_one_cm":735,"minecraft:walk_on_water_one_cm":622,"minecraft:sprint_one_cm":20487,"minecraft:play_time":4272,"minecraft:time_since_death":4272,"minecraft:walk_one_cm":7229,"minecraft:sneak_time":333,"minecraft:total_world_time":4272,"minecraft:walk_under_water_one_cm":168,"minecraft:fall_one_cm":3198,"minecraft:fly_one_cm":42939},"minecraft:mined":{"minecraft:crimson_roots":1}},"DataVersion":3337}