{"stats":{"minecraft:used":{"minecraft:netherite_axe":2,"minecraft:netherite_sword":7,"minecraft:ender_pearl":2,"minecraft:golden_apple":2,"minecraft:splash_potion":3},"minecraft:custom":{"minecraft:jump":43,"minecraft:leave_game":1,"minecraft:time_since_rest":1767,"minecraft:damage_taken":289,"minecraft:damage_absorbed":81,"minecraft:damage_dealt":119,"minecraft:sprint_one_cm":5798,"minecraft:play_time":1767,"minecraft:time_since_death":1767,"minecraft:walk_one_cm":7421,"minecraft:total_world_time":1767,"minecraft:damage_dealt_absorbed":81,"minecraft:fly_one_cm":8844}},"DataVersion":3337}