{"stats":{"minecraft:custom":{"minecraft:time_since_rest":3278,"minecraft:damage_taken":26889,"minecraft:crouch_one_cm":937,"minecraft:play_time":54450,"minecraft:sprint_one_cm":173590,"minecraft:damage_absorbed":6844,"minecraft:deaths":19,"minecraft:walk_one_cm":156502,"minecraft:sneak_time":582,"minecraft:damage_blocked_by_shield":1160,"minecraft:walk_under_water_one_cm":420,"minecraft:aviate_one_cm":1241,"minecraft:jump":1099,"minecraft:damage_dealt":2951,"minecraft:leave_game":2,"minecraft:walk_on_water_one_cm":50,"minecraft:time_since_death":3278,"minecraft:total_world_time":54450,"minecraft:damage_dealt_absorbed":7586,"minecraft:swim_one_cm":1961,"minecraft:fall_one_cm":101314,"minecraft:fly_one_cm":208948,"minecraft:player_kills":13},"minecraft:picked_up":{"minecraft:weeping_vines":3,"minecraft:dirt":523},"minecraft:used":{"minecraft:respawn_anchor":25,"minecraft:diamond_sword":49,"minecraft:golden_apple":63,"minecraft:netherite_sword":163,"minecraft:end_crystal":256,"minecraft:crossbow":3,"minecraft:ender_pearl":52,"minecraft:shield":6,"minecraft:cobweb":2,"minecraft:experience_bottle":64,"minecraft:splash_potion":14,"minecraft:totem_of_undying":87,"minecraft:obsidian":217,"minecraft:fishing_rod":14},"minecraft:killed_by":{"minecraft:player":19},"minecraft:mined":{"minecraft:grass_block":1,"minecraft:weeping_vines_plant":2,"minecraft:crimson_roots":1,"minecraft:dirt":37}},"DataVersion":3337}