{"stats":{"minecraft:killed_by":{"minecraft:player":2},"minecraft:custom":{"minecraft:time_since_rest":5339,"minecraft:deaths":2,"minecraft:walk_one_cm":221876,"minecraft:crouch_one_cm":1915,"minecraft:play_time":48364,"minecraft:sprint_one_cm":89699,"minecraft:damage_taken":11226,"minecraft:damage_absorbed":2476,"minecraft:sneak_time":2522,"minecraft:jump":604,"minecraft:damage_dealt":1405,"minecraft:leave_game":1,"minecraft:time_since_death":5338,"minecraft:total_world_time":48364,"minecraft:player_kills":5,"minecraft:damage_dealt_absorbed":1709,"minecraft:fall_one_cm":63256,"minecraft:fly_one_cm":106203},"minecraft:picked_up":{"minecraft:dirt":90},"minecraft:mined":{"minecraft:dirt":5},"minecraft:used":{"minecraft:netherite_sword":116,"minecraft:golden_apple":47,"minecraft:respawn_anchor":32,"minecraft:glowstone":5,"minecraft:end_crystal":56,"minecraft:netherite_axe":10,"minecraft:ender_pearl":75,"minecraft:splash_potion":9,"minecraft:experience_bottle":320,"minecraft:obsidian":93,"minecraft:totem_of_undying":25}},"DataVersion":3337}