{"stats":{"minecraft:used":{"minecraft:netherite_sword":16,"minecraft:golden_apple":4,"minecraft:diamond_sword":17,"minecraft:splash_potion":6},"minecraft:killed_by":{"minecraft:player":2},"minecraft:custom":{"minecraft:jump":92,"minecraft:leave_game":1,"minecraft:time_since_rest":142,"minecraft:damage_absorbed":159,"minecraft:damage_dealt":427,"minecraft:deaths":2,"minecraft:sprint_one_cm":15293,"minecraft:play_time":2537,"minecraft:damage_taken":927,"minecraft:time_since_death":142,"minecraft:walk_one_cm":10660,"minecraft:total_world_time":2537,"minecraft:damage_dealt_absorbed":114,"minecraft:fall_one_cm":211,"minecraft:fly_one_cm":13336}},"DataVersion":3337}