{"stats":{"minecraft:used":{"minecraft:golden_apple":10,"minecraft:netherite_sword":244,"minecraft:bow":15,"minecraft:ender_pearl":16,"minecraft:shield":1,"minecraft:splash_potion":27,"minecraft:experience_bottle":41},"minecraft:custom":{"minecraft:time_since_rest":22616,"minecraft:damage_absorbed":284,"minecraft:crouch_one_cm":277,"minecraft:walk_one_cm":42250,"minecraft:play_time":22616,"minecraft:sprint_one_cm":84683,"minecraft:damage_taken":508,"minecraft:damage_blocked_by_shield":240,"minecraft:sneak_time":54,"minecraft:jump":790,"minecraft:damage_dealt":4685,"minecraft:leave_game":3,"minecraft:time_since_death":22616,"minecraft:total_world_time":22616,"minecraft:damage_dealt_absorbed":1313,"minecraft:player_kills":5,"minecraft:fall_one_cm":2069,"minecraft:fly_one_cm":192095}},"DataVersion":3337}