{"entries":[{"playerName":"vulkai","playerDisplayName":"§f§lMEMBER §fvulkai§r","prefix":"\u0026f\u0026lMEMBER \u0026f","suffix":"","playerID":"6061bfb7-eccd-3ea8-a24b-0218d8338157","position":1,"board":"statistic_player_kills","type":"WEEKLY","score":577.0},{"playerName":"ITzsBG","playerDisplayName":"§f§lMEMBER §fITzsBG§r","prefix":"\u0026f\u0026lMEMBER \u0026f","suffix":"","playerID":"4caa6aa8-ab22-313d-a11e-4b00cf99113b","position":2,"board":"statistic_player_kills","type":"WEEKLY","score":430.0},{"playerName":"himanshu123opp","playerDisplayName":"§f§lMEMBER §fhimanshu123opp§r","prefix":"\u0026f\u0026lMEMBER \u0026f","suffix":"","playerID":"dbb10539-f2c1-353b-be7b-8e4cd0786b51","position":3,"board":"statistic_player_kills","type":"WEEKLY","score":315.0},{"playerName":"RexyJod","playerDisplayName":"§f§lMEMBER §fRexyJod§r","prefix":"\u0026f\u0026lMEMBER \u0026f","suffix":"","playerID":"578c4764-5528-37ea-95d7-411a8f5dd48c","position":4,"board":"statistic_player_kills","type":"WEEKLY","score":313.0},{"playerName":"NotSpooky_","playerDisplayName":"§f§lMEMBER §fNotSpooky_§r","prefix":"\u0026f\u0026lMEMBER \u0026f","suffix":"","playerID":"af989429-dab5-3e24-bdfd-c61467f67fcb","position":5,"board":"statistic_player_kills","type":"WEEKLY","score":297.0},{"playerName":"RKGAMER123456","playerDisplayName":"§f§lMEMBER §fRKGAMER123456§r","prefix":"\u0026f\u0026lMEMBER \u0026f","suffix":"","playerID":"07b1bc60-0df5-352c-b556-48d25d5eb64b","position":6,"board":"statistic_player_kills","type":"WEEKLY","score":286.0},{"playerName":"Unknown_BG_YT","playerDisplayName":"§f§lMEMBER §fUnknown_BG_YT§r","prefix":"\u0026f\u0026lMEMBER \u0026f","suffix":"","playerID":"e6dd5d0f-efca-31fa-b65f-86eea39ad27b","position":7,"board":"statistic_player_kills","type":"WEEKLY","score":273.0},{"playerName":"Dhruvgamer67","playerDisplayName":"§f§lMEMBER §fDhruvgamer67§r","prefix":"\u0026f\u0026lMEMBER \u0026f","suffix":"","playerID":"aa4b33d1-1512-32b9-af93-21a3a04ebf91","position":8,"board":"statistic_player_kills","type":"WEEKLY","score":272.0},{"playerName":"ORIGIN_THOR","playerDisplayName":"§f§lMEMBER §fORIGIN_THOR§r","prefix":"\u0026f\u0026lMEMBER \u0026f","suffix":"","playerID":"ded6a898-068d-32b7-adc2-7766ca55596a","position":9,"board":"statistic_player_kills","type":"WEEKLY","score":255.0},{"playerName":"JASHAN_DEVIL11","playerDisplayName":"§f§lMEMBER §fJASHAN_DEVIL11§r","prefix":"\u0026f\u0026lMEMBER \u0026f","suffix":"","playerID":"7abfaff5-0789-3d23-8c5d-14b6bafc09df","position":10,"board":"statistic_player_kills","type":"WEEKLY","score":241.0}],"meta":{"time":1694304001094,"type":"WEEKLY","board":"statistic_player_kills"}}