{"entries":[{"playerName":"donut369","playerDisplayName":"\u0026x§9§lV\u0026x§2§lI\u0026x§b§lP \u0026x§cdonut369§r","prefix":"\u0026x\u00260\u00266\u0026c\u00267\u0026a\u00269\u0026lV\u0026x\u00261\u00262\u00269\u00266\u0026d\u00262\u0026lI\u0026x\u00261\u0026d\u00266\u00264\u0026f\u0026b\u0026lP \u0026x\u00261\u0026d\u00266\u00264\u0026f\u0026c","suffix":"","playerID":"2cf4eac1-1169-3fc2-b8f6-212cab9ad9c4","position":1,"board":"statistic_hours_played","type":"WEEKLY","score":26.0},{"playerName":"PriceZamm","playerDisplayName":"§f§lPLAYER §7PriceZamm§r","prefix":"\u0026f\u0026lPLAYER \u00267","suffix":"","playerID":"6cbcee0e-927a-397a-b07c-ae881b17c2ec","position":2,"board":"statistic_hours_played","type":"WEEKLY","score":25.0},{"playerName":"PunishCriticals","playerDisplayName":"\u0026x§f§lM\u0026x§d§lE\u0026x§b§lD\u0026x§8§lI\u0026x§6§lA \u0026x§6PunishCriticals§r","prefix":"\u0026x\u0026f\u0026f\u00267\u00264\u00262\u0026f\u0026lM\u0026x\u0026f\u0026e\u00269\u00262\u00262\u0026d\u0026lE\u0026x\u0026f\u0026d\u0026b\u00260\u00262\u0026b\u0026lD\u0026x\u0026f\u0026c\u0026c\u0026e\u00262\u00268\u0026lI\u0026x\u0026f\u0026b\u0026e\u0026c\u00262\u00266\u0026lA \u0026x\u0026f\u0026c\u0026e\u0026c\u00262\u00266","suffix":"","playerID":"cc3f633c-d837-33c4-8fed-3d318d387655","position":3,"board":"statistic_hours_played","type":"WEEKLY","score":23.0},{"playerName":"DeadWarrior_OP","playerDisplayName":"§f§lPLAYER §7DeadWarrior_OP§r","prefix":"\u0026f\u0026lPLAYER \u00267","suffix":"","playerID":"35618722-9109-395e-95ee-0e70ad419c1e","position":4,"board":"statistic_hours_played","type":"WEEKLY","score":23.0},{"playerName":"PNBPN","playerDisplayName":"§f§lPLAYER §7PNBPN§r","prefix":"\u0026f\u0026lPLAYER \u00267","suffix":"","playerID":"543847f3-e012-3a46-85b5-7f904f3f267d","position":5,"board":"statistic_hours_played","type":"WEEKLY","score":22.0},{"playerName":"hiptip","playerDisplayName":"§f§lPLAYER §7hiptip§r","prefix":"\u0026f\u0026lPLAYER \u00267","suffix":"","playerID":"4014f718-a519-30e4-81ab-3f3c6101af6f","position":6,"board":"statistic_hours_played","type":"WEEKLY","score":21.0},{"playerName":"EgirlzErkoo","playerDisplayName":"§f§lPLAYER §7EgirlzErkoo§r","prefix":"\u0026f\u0026lPLAYER \u00267","suffix":"","playerID":"b9582f32-b83e-3104-bcd0-5ec846b6645c","position":7,"board":"statistic_hours_played","type":"WEEKLY","score":19.0},{"playerName":"Dead_Point_Op","playerDisplayName":"§f§lPLAYER §7Dead_Point_Op§r","prefix":"\u0026f\u0026lPLAYER \u00267","suffix":"","playerID":"a87b0d28-ff1a-36ac-bd0f-1cfc2c8473e0","position":8,"board":"statistic_hours_played","type":"WEEKLY","score":18.0},{"playerName":"xlwzp","playerDisplayName":"\u0026x§0§lF\u0026x§7§lL\u0026x§d§lO\u0026x§4§lX \u0026x§4xlwzp§r","prefix":"\u0026x\u0026f\u0026b\u00261\u00260\u0026c\u00260\u0026lF\u0026x\u0026f\u0026b\u00261\u00261\u00268\u00267\u0026lL\u0026x\u0026f\u0026b\u00261\u00263\u00264\u0026d\u0026lO\u0026x\u0026f\u0026b\u00261\u00264\u00261\u00264\u0026lX \u0026x\u0026f\u0026e\u00261\u00264\u00261\u00264","suffix":"","playerID":"4f41d15b-6df8-3c04-bb61-b6d09bd21804","position":9,"board":"statistic_hours_played","type":"WEEKLY","score":17.0},{"playerName":"LxGodz","playerDisplayName":"§f§lPLAYER §7LxGodz§r","prefix":"\u0026f\u0026lPLAYER \u00267","suffix":"","playerID":"5242edd6-a262-35f4-8ac0-7a7537c07f7e","position":10,"board":"statistic_hours_played","type":"WEEKLY","score":17.0}],"meta":{"time":1705170604231,"type":"WEEKLY","board":"statistic_hours_played"}}